nanos/__init__.py
nanos/data.py
nanos/debug.py
nanos/dt.py
nanos/fmt.py
nanos/logging.py
nanos/py.typed
nanos/time.py
nanos-0.1.8.dist-info/LICENSE
nanos-0.1.8.dist-info/METADATA
nanos-0.1.8.dist-info/WHEEL
nanos-0.1.8.dist-info/RECORD
