Metadata-Version: 2.1
Name: nanos
Version: 0.1.8
Summary: Collection of small utility-functions
Home-page: https://github.com/aleosd/nanos
License: Apache-2.0
Author: Alex
Author-email: aleosd@gmail.com
Requires-Python: >=3.10,<4.0
Classifier: Development Status :: 5 - Production/Stable
Classifier: License :: OSI Approved :: Apache Software License
Classifier: Programming Language :: Python :: 3
Classifier: Programming Language :: Python :: 3.10
Classifier: Programming Language :: Python :: 3.11
Classifier: Programming Language :: Python :: 3.12
Classifier: Topic :: Utilities
Project-URL: Documentation, https://nanos.readthedocs.io/en/stable/index.html
Project-URL: Repository, https://github.com/aleosd/nanos
